redsun/__init__.py
redsun/__main__.py
redsun/plugins.py
redsun/py.typed
redsun/common/__init__.py
redsun/common/qt.py
redsun/controller/__init__.py
redsun/controller/factory.py
redsun/controller/hardware.py
redsun/view/__init__.py
redsun/view/qt/__init__.py
redsun/view/qt/mainview.py
redsun-0.4.0.dist-info/METADATA
redsun-0.4.0.dist-info/WHEEL
redsun-0.4.0.dist-info/entry_points.txt
redsun-0.4.0.dist-info/licenses/LICENSE
redsun-0.4.0.dist-info/RECORD
