Metadata-Version: 2.4
Name: redsun
Version: 0.4.0
Summary: Event-driven data acquisition software for scientific applications.
Project-URL: bugs, https://github.com/redsun-acquisition/redsun/issues
Project-URL: changelog, https://github.com/redsun-acquisition/redsun/blob/master/changelog.md
Project-URL: homepage, https://github.com/redsun-acquisition/redsun
Author-email: Jacopo Abramo <jacopo.abramo@gmail.com>
Maintainer-email: Jacopo Abramo <jacopo.abramo@gmail.com>
License: Apache-2.0
License-File: LICENSE
Classifier: Development Status :: 3 - Alpha
Classifier: Intended Audience :: Developers
Classifier: Intended Audience :: Science/Research
Classifier: License :: OSI Approved :: Apache Software License
Classifier: Programming Language :: Python :: 3
Classifier: Programming Language :: Python :: 3.10
Classifier: Programming Language :: Python :: 3.11
Classifier: Programming Language :: Python :: 3.12
Classifier: Programming Language :: Python :: 3.13
Classifier: Programming Language :: Python :: Implementation :: CPython
Classifier: Topic :: Scientific/Engineering
Classifier: Typing :: Typed
Requires-Python: >=3.10
Requires-Dist: platformdirs>=4.3.8
Requires-Dist: sunflare>=0.7.0
Provides-Extra: dev
Requires-Dist: mypy>=1.19.1; extra == 'dev'
Requires-Dist: pre-commit>=4.5.0; extra == 'dev'
Requires-Dist: pytest-cov>=6.2.1; extra == 'dev'
Requires-Dist: pytest>=8.4.1; extra == 'dev'
Requires-Dist: ruff>=0.12.2; extra == 'dev'
Requires-Dist: sunflare[pyqt]>=0.7.0; extra == 'dev'
Provides-Extra: docs
Requires-Dist: myst-parser; extra == 'docs'
Requires-Dist: pydata-sphinx-theme; extra == 'docs'
Requires-Dist: sphinx; extra == 'docs'
Requires-Dist: sphinx-design; extra == 'docs'
Provides-Extra: pyqt
Requires-Dist: sunflare[pyqt]; extra == 'pyqt'
Provides-Extra: pyside
Requires-Dist: sunflare[pyside]; extra == 'pyside'
